{"computer-basic_design-pattern_index.md":"4a249d16","computer-basic_fucking-arithmetic_index.md":"6f4218e1","computer-basic_internet_index.md":"9b481dc3","front-end_browser_index.md":"c1884b7b","front-end_canvas_index.md":"f7f6415f","front-end_css_index.md":"f6a37264","front-end_git_index.md":"013aff03","front-end_html_index.md":"8b7f05e7","front-end_js_faq.md":"21d474bf","front-end_js_index.md":"a72ae1dd","front-end_nodejs_index.md":"554cd7a8","front-end_ts_faq.md":"08bd1f85","front-end_ts_index.md":"ee75e4dd","front-end_vue_index.md":"7cdab096","index.md":"ca86d202","knowledge-map.md":"2c4ae754","plan_multistage-routing_index.md":"8ca4bac5","plan_virtual-scroll_index.md":"0779a6be","tools_slides.md":"e9675c34"}
